{
    "Dumpster": {
        "title": "Jeremys' Dumpster",
        "image": "https://cdn.discordapp.com/attachments/497302646521069570/738367060115193866/supermarket.png",
        "suggestedLevel": "2",
        "successRate": {
            "1": 0.35,
            "2": 0.4,
            "3": 0.45,
            "4": 0.5,
            "5": 0.5,
            "6": 0.52,
            "7": 0.55,
            "8": 0.6,
            "9": 0.62,
            "10": 0.65
        },
        "requirement": {
            "type": null,
            "value": "",
            "bonus": 0
        },
        "success": [
            {
                "reward": {
                    "item": "crate|1",
                    "rareItem": "crate|1",
                    "money": {
                        "min": 2500,
                        "max": 4000
                    }
                },
                "loss": {
                    "type": null,
                    "value": 0
                },
                "quote": "**{user}** found {reward} outside of the dumpster!"
            },
            {
                "reward": {
                    "item": "crate|1",
                    "rareItem": "crate|1",
                    "money": {
                        "min": 2500,
                        "max": 4000
                    }
                },
                "loss": {
                    "type": null,
                    "value": 0
                },
                "quote": "**{user}** climbs on top of the dumpster and finds {reward}!"
            },
            {
                "reward": {
                    "item": "crate|1",
                    "rareItem": "crate|1",
                    "money": {
                        "min": 2500,
                        "max": 4000
                    }
                },
                "loss": {
                    "type": null,
                    "value": 0
                },
                "quote": "**{user}** loots a dead player inside the dumpster and finds {reward}!"
            }
        ],
        "failed": [
            {
                "loss": {
                    "type": null,
                    "value": 0
                },
                "item": "",
                "item2": "",
                "quote": "**{user}** saw people inside and was too scared to enter..."
            },
            {
                "loss": {
                    "type": null,
                    "value": 0
                },
                "item": "",
                "item2": "",
                "quote": "**{user}** could not find anything worth taking..."
            },
            {
                "loss": {
                    "type": null,
                    "value": 0
                },
                "item": "",
                "item2": "",
                "quote": "**{user}** could not find anything useful."
            },
            {
                "loss": {
                    "type": null,
                    "value": 0
                },
                "item": "",
                "item2": "",
                "quote": "All **{user}** saw was trash, empty bags and a dead rat."
            },
            {
                "loss": {
                    "type": null,
                    "value": 0
                },
                "item": "",
                "item2": "",
                "quote": "**{user}** checked all the bags, but found nothing..."
            },
            {
                "loss": {
                    "type": "health",
                    "value": 4
                },
                "item": "rock",
                "item2": "",
                "quote": "Someone bonked **{user}** on the head with a {item} for **{damage}** damage, and ran away!"
            },
            {
                "loss": {
                    "type": "health",
                    "value": 5
                },
                "item": "crowbar",
                "item2": "",
                "quote": "**{user}** got into a fight with an armed man wielding a {item} and lost **{damage}** health."
            },
            {
                "loss": {
                    "type": "health",
                    "value": 8
                },
                "item": "crossbow",
                "item2": "",
                "quote": "**{user}** was headshot by some loser with a {item} and lost **{damage}** health..."
            }
        ]
    }
}